flaui/__init__.py
flaui/bin/FlaUI.Core.dll
flaui/bin/FlaUI.UIA2.dll
flaui/bin/FlaUI.UIA3.dll
flaui/bin/Interop.UIAutomationClient.dll
flaui/bin/Version.md
flaui/lib/__init__.py
flaui/lib/cast_type_converter.py
flaui/lib/config.py
flaui/lib/enums.py
flaui/lib/pythonnet_bridge.py
flaui/wrappers/__init__.py
flaui/wrappers/core/__init__.py
flaui/wrappers/core/applicaiton.py
flaui/wrappers/core/automation.py
flaui/wrappers/core/automation_element_extensions.py
flaui/wrappers/core/automation_elements.py
flaui/wrappers/ui_automation.py
flaui_uiautomation_wrapper-0.1.1.dist-info/LICENSE
flaui_uiautomation_wrapper-0.1.1.dist-info/METADATA
flaui_uiautomation_wrapper-0.1.1.dist-info/WHEEL
flaui_uiautomation_wrapper-0.1.1.dist-info/RECORD
