Metadata-Version: 2.1
Name: flaui-uiautomation-wrapper
Version: 0.1.1
Summary: Tool to perform UI Automation on Windows desktop applications using an underlying FlaUI wrapper.
Home-page: https://github.com/amruthvvkp/flaui-uiautomation-wrapper
License: LGPL-3.0-or-later
Keywords: testing,ui,ui-automation,automation,windows,windows automation,windows testing,desktop automation,flaui,qa
Author: Amruth VVKP
Author-email: amruthvvkp@gmail.com
Requires-Python: >=3.7,<3.12
Classifier: Development Status :: 3 - Alpha
Classifier: Intended Audience :: Developers
Classifier: License :: OSI Approved :: GNU Lesser General Public License v3 or later (LGPLv3+)
Classifier: Operating System :: MacOS :: MacOS X
Classifier: Operating System :: Microsoft :: Windows
Classifier: Operating System :: POSIX :: Linux
Classifier: Programming Language :: Python :: 3
Classifier: Programming Language :: Python :: 3.7
Classifier: Programming Language :: Python :: 3.8
Classifier: Programming Language :: Python :: 3.9
Classifier: Programming Language :: Python :: 3.10
Classifier: Programming Language :: Python :: 3.11
Classifier: Programming Language :: Python :: 3 :: Only
Classifier: Topic :: Software Development :: Libraries :: Python Modules
Classifier: Topic :: Software Development :: Quality Assurance
Classifier: Topic :: Software Development :: Testing
Classifier: Topic :: Utilities
Classifier: Typing :: Typed
Requires-Dist: arrow (>=1.2.3,<2.0.0)
Requires-Dist: loguru (>=0.6.0,<0.7.0)
Requires-Dist: pillow (>=9.3.0,<10.0.0)
Requires-Dist: pydantic (>=2.0.0,<3.0.0)
Requires-Dist: pydantic-extra-types (>=2.0.0,<3.0.0)
Requires-Dist: pydantic-settings (>=2.0.0,<3.0.0)
Requires-Dist: pythonnet (>=3.0.1,<4.0.0)
Project-URL: Repository, https://github.com/amruthvvkp/flaui-uiautomation-wrapper
